aibaba_ai_api/__init__.py
aibaba_ai_api/_pydantic.py
aibaba_ai_api/api_handler.py
aibaba_ai_api/callbacks.py
aibaba_ai_api/chat_playground/.eslintrc.cjs
aibaba_ai_api/chat_playground/.gitignore
aibaba_ai_api/chat_playground/README.md
aibaba_ai_api/chat_playground/dist/assets/index-434ff580.css
aibaba_ai_api/chat_playground/dist/assets/index-53ad47d4.js
aibaba_ai_api/chat_playground/dist/favicon.ico
aibaba_ai_api/chat_playground/dist/index.html
aibaba_ai_api/chat_playground/index.html
aibaba_ai_api/chat_playground/package.json
aibaba_ai_api/chat_playground/postcss.config.js
aibaba_ai_api/chat_playground/public/favicon.ico
aibaba_ai_api/chat_playground/src/App.css
aibaba_ai_api/chat_playground/src/App.tsx
aibaba_ai_api/chat_playground/src/assets/ArrowUp.svg
aibaba_ai_api/chat_playground/src/assets/ChatIcon.svg
aibaba_ai_api/chat_playground/src/assets/CheckCircleIcon.svg
aibaba_ai_api/chat_playground/src/assets/CheckCircleIcon2.svg
aibaba_ai_api/chat_playground/src/assets/ChevronRight.svg
aibaba_ai_api/chat_playground/src/assets/CircleSpinIcon.svg
aibaba_ai_api/chat_playground/src/assets/CodeIcon.svg
aibaba_ai_api/chat_playground/src/assets/CopyIcon.svg
aibaba_ai_api/chat_playground/src/assets/EmptyState.svg
aibaba_ai_api/chat_playground/src/assets/LangServeLogo.svg
aibaba_ai_api/chat_playground/src/assets/PadlockIcon.svg
aibaba_ai_api/chat_playground/src/assets/PlusIcon.svg
aibaba_ai_api/chat_playground/src/assets/RefreshCW.svg
aibaba_ai_api/chat_playground/src/assets/SendIcon.svg
aibaba_ai_api/chat_playground/src/assets/ShareIcon.svg
aibaba_ai_api/chat_playground/src/assets/ThumbsDownIcon.svg
aibaba_ai_api/chat_playground/src/assets/ThumbsUpIcon.svg
aibaba_ai_api/chat_playground/src/assets/TrashIcon.svg
aibaba_ai_api/chat_playground/src/assets/XCircle.svg
aibaba_ai_api/chat_playground/src/components/AutosizeTextarea.tsx
aibaba_ai_api/chat_playground/src/components/ChatMessage.tsx
aibaba_ai_api/chat_playground/src/components/ChatWindow.tsx
aibaba_ai_api-0.3.3.dist-info/LICENSE
aibaba_ai_api-0.3.3.dist-info/METADATA
aibaba_ai_api-0.3.3.dist-info/WHEEL
aibaba_ai_api-0.3.3.dist-info/RECORD
