Metadata-Version: 2.3
Name: aibaba_ai_api
Version: 0.3.3
Summary: 
License: aibaba-ai-api
Author: Aibaba AI
Requires-Python: >=3.9,<4.0
Classifier: License :: Other/Proprietary License
Classifier: Programming Language :: Python :: 3
Classifier: Programming Language :: Python :: 3.9
Classifier: Programming Language :: Python :: 3.10
Classifier: Programming Language :: Python :: 3.11
Classifier: Programming Language :: Python :: 3.12
Classifier: Programming Language :: Python :: 3.13
Provides-Extra: all
Provides-Extra: client
Provides-Extra: server
Requires-Dist: aibaba_ai_core (>=0.3.31,<0.4.0)
Requires-Dist: fastapi (>=0.90.1,<1) ; extra == "client" or extra == "server" or extra == "all"
Requires-Dist: httpx (>=0.23.0,<1.0)
Requires-Dist: orjson (>=2,<4)
Requires-Dist: pydantic (>=2.7,<3.0)
Requires-Dist: sse-starlette (>=1.3.0,<2.0.0) ; extra == "server" or extra == "all"
Project-URL: Repository, https://github.com/aibaba-ai/aibaba-ai
